<?xml version='1.0' encoding='UTF-8' standalone='yes' ?><wifiScanResults generator="com.farproc.wifi.analyzer (3.10.1-L)" generatorUrl="market://details?id=com.farproc.wifi.analyzer" number="20"><scanResult SSID="eduroam" BSSID="00:3a:7d:a2:7d:ef" capabilities="[WPA2-EAP-CCMP][ESS]" frequency="5660" level="-44" centerFreq0="5680" centerFreq1="0" channelWidth="40" operatorFriendlyName="" venueName="" is80211mcResponder="false" isPasspointNetwork="false" /><scanResult SSID="eduroam" BSSID="00:3a:7d:75:38:6f" capabilities="[WPA2-EAP-CCMP][ESS]" frequency="5220" level="-59" centerFreq0="5240" centerFreq1="0" channelWidth="40" operatorFriendlyName="" venueName="" is80211mcResponder="false" isPasspointNetwork="false" /><scanResult SSID="eduroam" BSSID="00:35:1a:5b:86:7f" capabilities="[WPA2-EAP-CCMP][ESS]" frequency="5540" level="-71" centerFreq0="5560" centerFreq1="0" channelWidth="40" operatorFriendlyName="" venueName="" is80211mcResponder="false" isPasspointNetwork="false" /><scanResult SSID="eduroam" BSSID="78:ba:f9:cf:3c:2f" capabilities="[WPA2-EAP-CCMP][ESS]" frequency="5180" level="-75" centerFreq0="5200" centerFreq1="0" channelWidth="40" operatorFriendlyName="" venueName="" is80211mcResponder="false" isPasspointNetwork="false" /><scanResult SSID="eduroam" BSSID="00:3a:7d:a2:7d:e0" capabilities="[WPA2-EAP-CCMP][ESS]" frequency="2462" level="-53" centerFreq0="0" centerFreq1="0" channelWidth="22" operatorFriendlyName="" venueName="" is80211mcResponder="false" isPasspointNetwork="false" /><scanResult SSID="eduroam" BSSID="00:3a:7d:75:38:60" capabilities="[WPA2-EAP-CCMP][ESS]" frequency="2412" level="-65" centerFreq0="0" centerFreq1="0" channelWidth="22" operatorFriendlyName="" venueName="" is80211mcResponder="false" isPasspointNetwork="false" /><scanResult SSID="eduroam" BSSID="78:ba:f9:cf:3c:20" capabilities="[WPA2-EAP-CCMP][ESS]" frequency="2437" level="-69" centerFreq0="0" centerFreq1="0" channelWidth="22" operatorFriendlyName="" venueName="" is80211mcResponder="false" isPasspointNetwork="false" /><scanResult SSID="G19A" BSSID="00:11:50:c7:15:c1" capabilities="[WPA-PSK-TKIP][ESS]" frequency="2462" level="-69" centerFreq0="0" centerFreq1="0" channelWidth="22" operatorFriendlyName="" venueName="" is80211mcResponder="false" isPasspointNetwork="false" /><scanResult SSID="eduroam" BSSID="00:35:1a:5b:86:70" capabilities="[WPA2-EAP-CCMP][ESS]" frequency="2437" level="-79" centerFreq0="0" centerFreq1="0" channelWidth="22" operatorFriendlyName="" venueName="" is80211mcResponder="false" isPasspointNetwork="false" /><scanResult SSID="UCLGuest" BSSID="00:3a:7d:a2:7d:ed" capabilities="[ESS]" frequency="5660" level="-44" centerFreq0="5680" centerFreq1="0" channelWidth="40" operatorFriendlyName="" venueName="" is80211mcResponder="false" isPasspointNetwork="false" /><scanResult SSID="UCLGuest" BSSID="00:3a:7d:75:38:6d" capabilities="[ESS]" frequency="5220" level="-60" centerFreq0="5240" centerFreq1="0" channelWidth="40" operatorFriendlyName="" venueName="" is80211mcResponder="false" isPasspointNetwork="false" /><scanResult SSID="UCLGuest" BSSID="00:35:1a:5b:86:7d" capabilities="[ESS]" frequency="5540" level="-71" centerFreq0="5560" centerFreq1="0" channelWidth="40" operatorFriendlyName="" venueName="" is80211mcResponder="false" isPasspointNetwork="false" /><scanResult SSID="UCLGuest" BSSID="78:ba:f9:cf:3c:2d" capabilities="[ESS]" frequency="5180" level="-75" centerFreq0="5200" centerFreq1="0" channelWidth="40" operatorFriendlyName="" venueName="" is80211mcResponder="false" isPasspointNetwork="false" /><scanResult SSID="UCLGuest" BSSID="00:3a:7d:a2:7d:e2" capabilities="[ESS]" frequency="2462" level="-53" centerFreq0="0" centerFreq1="0" channelWidth="22" operatorFriendlyName="" venueName="" is80211mcResponder="false" isPasspointNetwork="false" /><scanResult SSID="UCLGuest" BSSID="00:3a:7d:75:38:62" capabilities="[ESS]" frequency="2412" level="-64" centerFreq0="0" centerFreq1="0" channelWidth="22" operatorFriendlyName="" venueName="" is80211mcResponder="false" isPasspointNetwork="false" /><scanResult SSID="UCLGuest" BSSID="78:ba:f9:cf:3c:22" capabilities="[ESS]" frequency="2437" level="-68" centerFreq0="0" centerFreq1="0" channelWidth="22" operatorFriendlyName="" venueName="" is80211mcResponder="false" isPasspointNetwork="false" /><scanResult SSID="UCLGuest" BSSID="00:35:1a:5b:86:72" capabilities="[ESS]" frequency="2437" level="-79" centerFreq0="0" centerFreq1="0" channelWidth="22" operatorFriendlyName="" venueName="" is80211mcResponder="false" isPasspointNetwork="false" /><scanResult SSID="Service wifi" BSSID="74:ea:3a:d6:a2:78" capabilities="[WPA-PSK-CCMP][WPA2-PSK-CCMP][WPS][ESS]" frequency="2427" level="-86" centerFreq0="2447" centerFreq1="0" channelWidth="40" operatorFriendlyName="" venueName="" is80211mcResponder="false" isPasspointNetwork="false" /><scanResult SSID="Apple Network (ASW) 8d5250" BSSID="00:25:bc:8d:52:4f" capabilities="[WPA2-PSK-CCMP][ESS]" frequency="2462" level="-88" centerFreq0="0" centerFreq1="0" channelWidth="22" operatorFriendlyName="" venueName="" is80211mcResponder="false" isPasspointNetwork="false" /><scanResult SSID="UCLGuest" BSSID="00:22:90:50:f2:c2" capabilities="[ESS]" frequency="2412" level="-93" centerFreq0="0" centerFreq1="0" channelWidth="22" operatorFriendlyName="" venueName="" is80211mcResponder="false" isPasspointNetwork="false" /></wifiScanResults>